smcore/VERSION
smcore/__init__.py
smcore/agent.py
smcore/core.py
smcore/deserialize.py
smcore/filter.py
smcore/hardcore.py
smcore/hardcore_post.py
smcore/http_transit.py
smcore/listen.py
smcore/postgres_transit.py
smcore/project.py
smcore/replay.py
smcore/serialize.py
smcore/sqlite_transit.py
smcore/tag_set.py
smcore/version.py
smcore-1.1.0.dist-info/METADATA
smcore-1.1.0.dist-info/WHEEL
smcore-1.1.0.dist-info/top_level.txt
smcore-1.1.0.dist-info/RECORD
