Metadata-Version: 2.4
Name: smcore
Version: 1.1.0
Summary: package providing core agent classes
Author-email: "J. Hoffman, J. Genender" <johnmarianhoffman@gmail.com>
Project-URL: Homepage, https://gitlab.com/hoffman-lab/core-py
Project-URL: Bug Tracker, https://gitlab.com/hoffman-lab/core-py/issues
Classifier: Programming Language :: Python :: 3
Classifier: Operating System :: OS Independent
Requires-Python: >=3.9
Requires-Dist: aiohttp
Requires-Dist: vyper-config
Requires-Dist: numpy
Requires-Dist: psycopg2-binary
